demo/__init__.py
demo/main.py
zjunweidemo-0.0.1.dist-info/METADATA
zjunweidemo-0.0.1.dist-info/WHEEL
zjunweidemo-0.0.1.dist-info/top_level.txt
zjunweidemo-0.0.1.dist-info/RECORD
