Metadata-Version: 2.1
Name: zjunweidemo
Version: 0.0.1
Summary: A demo for python packaging.
Home-page: UNKNOWN
Author: zjunwei
Author-email: zjunweihit@163.com
License: MIT
Keywords: demo
Platform: UNKNOWN
